Patrick_personnal_library/DB_manipulation.py
Patrick_personnal_library/Installer_module.py
Patrick_personnal_library/__init__.py
Patrick_personnal_library/ask_path_save_load.py
Patrick_personnal_library/excel_utils.py
Patrick_personnal_library-0.1.0.dist-info/LICENSE
Patrick_personnal_library-0.1.0.dist-info/METADATA
Patrick_personnal_library-0.1.0.dist-info/WHEEL
Patrick_personnal_library-0.1.0.dist-info/top_level.txt
Patrick_personnal_library-0.1.0.dist-info/RECORD
