Metadata-Version: 2.1
Name: Patrick-personnal-library
Version: 0.1.0
Summary: tout ce que j'ai besoin
Home-page: https://github.com/Psychopatd/Patrick_personnal_library.git
Author: Patrick
Author-email: pdionne.83@gmail.com
Classifier: Programming Language :: Python :: 3
Classifier: License :: OSI Approved :: MIT License
Classifier: Operating System :: OS Independent
Requires-Python: >=3.6
License-File: LICENSE
